erp3_py_commons/__init__.py
erp3_py_commons/anexo/__init__.py
erp3_py_commons/anexo/anexo_controller.py
erp3_py_commons/anexo/anexo_dao.py
erp3_py_commons/anexo/anexo_dto.py
erp3_py_commons/anexo/anexo_service.py
erp3_py_commons-0.0.7.dist-info/METADATA
erp3_py_commons-0.0.7.dist-info/WHEEL
erp3_py_commons-0.0.7.dist-info/top_level.txt
erp3_py_commons-0.0.7.dist-info/RECORD
