Metadata-Version: 2.1
Name: erp3-py-commons
Version: 0.0.7
Summary: Utilitários python comuns a diversos aplicativos relacionados ao BD desktop (para APIs multibanco).
Home-page: https://github.com/Nasajon/erp3-py-commons
Author: Nasajon Sistemas
Author-email: contact.dev@nasajon.com.br
Project-URL: Source, https://github.com/Nasajon/erp3-py-commons
Classifier: Development Status :: 3 - Alpha
Classifier: Intended Audience :: Developers
Classifier: Topic :: Software Development :: Libraries
Classifier: Programming Language :: Python :: 3
Requires-Python: >=3.4
Requires-Dist: Flask<3.0.0,>=2.0.3
Requires-Dist: nsj-rest-lib<3.0.0,>=2.10.0
